[
  {
    "country_iso2": "DK",
    "source": "worldbank",
    "indicator_code": "NY.GDP.PCAP.KD",
    "period": "2024-01-01",
    "value": 63229.9479713724,
    "meta": {
      "unit": "",
      "obs_status": "",
      "decimal": 1,
      "country_name": "Denmark",
      "indicator_name": "GDP per capita (constant 2015 US$)"
    }
  },
  {
    "country_iso2": "DK",
    "source": "worldbank",
    "indicator_code": "NY.GDP.PCAP.KD",
    "period": "2023-01-01",
    "value": 61295.9818625045,
    "meta": {
      "unit": "",
      "obs_status": "",
      "decimal": 1,
      "country_name": "Denmark",
      "indicator_name": "GDP per capita (constant 2015 US$)"
    }
  },
  {
    "country_iso2": "DK",
    "source": "worldbank",
    "indicator_code": "NY.GDP.PCAP.KD",
    "period": "2022-01-01",
    "value": 60248.671222365,
    "meta": {
      "unit": "",
      "obs_status": "",
      "decimal": 1,
      "country_name": "Denmark",
      "indicator_name": "GDP per capita (constant 2015 US$)"
    }
  },
  {
    "country_iso2": "DK",
    "source": "worldbank",
    "indicator_code": "NY.GDP.PCAP.KD",
    "period": "2021-01-01",
    "value": 59803.9202218941,
    "meta": {
      "unit": "",
      "obs_status": "",
      "decimal": 1,
      "country_name": "Denmark",
      "indicator_name": "GDP per capita (constant 2015 US$)"
    }
  },
  {
    "country_iso2": "DK",
    "source": "worldbank",
    "indicator_code": "NY.GDP.PCAP.KD",
    "period": "2020-01-01",
    "value": 55934.5555945523,
    "meta": {
      "unit": "",
      "obs_status": "",
      "decimal": 1,
      "country_name": "Denmark",
      "indicator_name": "GDP per capita (constant 2015 US$)"
    }
  },
  {
    "country_iso2": "DK",
    "source": "worldbank",
    "indicator_code": "NY.GDP.PCAP.KD",
    "period": "2019-01-01",
    "value": 57114.6227336347,
    "meta": {
      "unit": "",
      "obs_status": "",
      "decimal": 1,
      "country_name": "Denmark",
      "indicator_name": "GDP per capita (constant 2015 US$)"
    }
  },
  {
    "country_iso2": "DK",
    "source": "worldbank",
    "indicator_code": "NY.GDP.PCAP.KD",
    "period": "2018-01-01",
    "value": 56355.0733084714,
    "meta": {
      "unit": "",
      "obs_status": "",
      "decimal": 1,
      "country_name": "Denmark",
      "indicator_name": "GDP per capita (constant 2015 US$)"
    }
  },
  {
    "country_iso2": "DK",
    "source": "worldbank",
    "indicator_code": "NY.GDP.PCAP.KD",
    "period": "2017-01-01",
    "value": 55601.0145717787,
    "meta": {
      "unit": "",
      "obs_status": "",
      "decimal": 1,
      "country_name": "Denmark",
      "indicator_name": "GDP per capita (constant 2015 US$)"
    }
  },
  {
    "country_iso2": "DK",
    "source": "worldbank",
    "indicator_code": "NY.GDP.PCAP.KD",
    "period": "2016-01-01",
    "value": 54300.2039621991,
    "meta": {
      "unit": "",
      "obs_status": "",
      "decimal": 1,
      "country_name": "Denmark",
      "indicator_name": "GDP per capita (constant 2015 US$)"
    }
  },
  {
    "country_iso2": "DK",
    "source": "worldbank",
    "indicator_code": "NY.GDP.PCAP.KD",
    "period": "2015-01-01",
    "value": 53094.0133607574,
    "meta": {
      "unit": "",
      "obs_status": "",
      "decimal": 1,
      "country_name": "Denmark",
      "indicator_name": "GDP per capita (constant 2015 US$)"
    }
  },
  {
    "country_iso2": "DK",
    "source": "worldbank",
    "indicator_code": "NY.GDP.MKTP.KD.ZG",
    "period": "2024-01-01",
    "value": 3.67619734971929,
    "meta": {
      "unit": "",
      "obs_status": "",
      "decimal": 1,
      "country_name": "Denmark",
      "indicator_name": "GDP growth (annual %)"
    }
  },
  {
    "country_iso2": "DK",
    "source": "worldbank",
    "indicator_code": "NY.GDP.MKTP.KD.ZG",
    "period": "2023-01-01",
    "value": 2.49518434516773,
    "meta": {
      "unit": "",
      "obs_status": "",
      "decimal": 1,
      "country_name": "Denmark",
      "indicator_name": "GDP growth (annual %)"
    }
  },
  {
    "country_iso2": "DK",
    "source": "worldbank",
    "indicator_code": "NY.GDP.MKTP.KD.ZG",
    "period": "2022-01-01",
    "value": 1.54017307357893,
    "meta": {
      "unit": "",
      "obs_status": "",
      "decimal": 1,
      "country_name": "Denmark",
      "indicator_name": "GDP growth (annual %)"
    }
  },
  {
    "country_iso2": "DK",
    "source": "worldbank",
    "indicator_code": "NY.GDP.MKTP.KD.ZG",
    "period": "2021-01-01",
    "value": 7.38206633449863,
    "meta": {
      "unit": "",
      "obs_status": "",
      "decimal": 1,
      "country_name": "Denmark",
      "indicator_name": "GDP growth (annual %)"
    }
  },
  {
    "country_iso2": "DK",
    "source": "worldbank",
    "indicator_code": "NY.GDP.MKTP.KD.ZG",
    "period": "2020-01-01",
    "value": -1.78010601831291,
    "meta": {
      "unit": "",
      "obs_status": "",
      "decimal": 1,
      "country_name": "Denmark",
      "indicator_name": "GDP growth (annual %)"
    }
  },
  {
    "country_iso2": "DK",
    "source": "worldbank",
    "indicator_code": "NY.GDP.MKTP.KD.ZG",
    "period": "2019-01-01",
    "value": 1.71140093932736,
    "meta": {
      "unit": "",
      "obs_status": "",
      "decimal": 1,
      "country_name": "Denmark",
      "indicator_name": "GDP growth (annual %)"
    }
  },
  {
    "country_iso2": "DK",
    "source": "worldbank",
    "indicator_code": "NY.GDP.MKTP.KD.ZG",
    "period": "2018-01-01",
    "value": 1.8600074900921,
    "meta": {
      "unit": "",
      "obs_status": "",
      "decimal": 1,
      "country_name": "Denmark",
      "indicator_name": "GDP growth (annual %)"
    }
  },
  {
    "country_iso2": "DK",
    "source": "worldbank",
    "indicator_code": "NY.GDP.MKTP.KD.ZG",
    "period": "2017-01-01",
    "value": 3.05647723922718,
    "meta": {
      "unit": "",
      "obs_status": "",
      "decimal": 1,
      "country_name": "Denmark",
      "indicator_name": "GDP growth (annual %)"
    }
  },
  {
    "country_iso2": "DK",
    "source": "worldbank",
    "indicator_code": "NY.GDP.MKTP.KD.ZG",
    "period": "2016-01-01",
    "value": 3.07304549209093,
    "meta": {
      "unit": "",
      "obs_status": "",
      "decimal": 1,
      "country_name": "Denmark",
      "indicator_name": "GDP growth (annual %)"
    }
  },
  {
    "country_iso2": "DK",
    "source": "worldbank",
    "indicator_code": "NY.GDP.MKTP.KD.ZG",
    "period": "2015-01-01",
    "value": 2.10441456445301,
    "meta": {
      "unit": "",
      "obs_status": "",
      "decimal": 1,
      "country_name": "Denmark",
      "indicator_name": "GDP growth (annual %)"
    }
  },
  {
    "country_iso2": "DK",
    "source": "worldbank",
    "indicator_code": "FP.CPI.TOTL.ZG",
    "period": "2024-01-01",
    "value": 1.37220049768918,
    "meta": {
      "unit": "",
      "obs_status": "",
      "decimal": 1,
      "country_name": "Denmark",
      "indicator_name": "Inflation, consumer prices (annual %)"
    }
  },
  {
    "country_iso2": "DK",
    "source": "worldbank",
    "indicator_code": "FP.CPI.TOTL.ZG",
    "period": "2023-01-01",
    "value": 3.30517811237606,
    "meta": {
      "unit": "",
      "obs_status": "",
      "decimal": 1,
      "country_name": "Denmark",
      "indicator_name": "Inflation, consumer prices (annual %)"
    }
  },
  {
    "country_iso2": "DK",
    "source": "worldbank",
    "indicator_code": "FP.CPI.TOTL.ZG",
    "period": "2022-01-01",
    "value": 7.6965669988926,
    "meta": {
      "unit": "",
      "obs_status": "",
      "decimal": 1,
      "country_name": "Denmark",
      "indicator_name": "Inflation, consumer prices (annual %)"
    }
  },
  {
    "country_iso2": "DK",
    "source": "worldbank",
    "indicator_code": "FP.CPI.TOTL.ZG",
    "period": "2021-01-01",
    "value": 1.8530454398968,
    "meta": {
      "unit": "",
      "obs_status": "",
      "decimal": 1,
      "country_name": "Denmark",
      "indicator_name": "Inflation, consumer prices (annual %)"
    }
  },
  {
    "country_iso2": "DK",
    "source": "worldbank",
    "indicator_code": "FP.CPI.TOTL.ZG",
    "period": "2020-01-01",
    "value": 0.420711974110115,
    "meta": {
      "unit": "",
      "obs_status": "",
      "decimal": 1,
      "country_name": "Denmark",
      "indicator_name": "Inflation, consumer prices (annual %)"
    }
  },
  {
    "country_iso2": "DK",
    "source": "worldbank",
    "indicator_code": "FP.CPI.TOTL.ZG",
    "period": "2019-01-01",
    "value": 0.75813157251162,
    "meta": {
      "unit": "",
      "obs_status": "",
      "decimal": 1,
      "country_name": "Denmark",
      "indicator_name": "Inflation, consumer prices (annual %)"
    }
  },
  {
    "country_iso2": "DK",
    "source": "worldbank",
    "indicator_code": "FP.CPI.TOTL.ZG",
    "period": "2018-01-01",
    "value": 0.813609467455631,
    "meta": {
      "unit": "",
      "obs_status": "",
      "decimal": 1,
      "country_name": "Denmark",
      "indicator_name": "Inflation, consumer prices (annual %)"
    }
  },
  {
    "country_iso2": "DK",
    "source": "worldbank",
    "indicator_code": "FP.CPI.TOTL.ZG",
    "period": "2017-01-01",
    "value": 1.14713216957602,
    "meta": {
      "unit": "",
      "obs_status": "",
      "decimal": 1,
      "country_name": "Denmark",
      "indicator_name": "Inflation, consumer prices (annual %)"
    }
  },
  {
    "country_iso2": "DK",
    "source": "worldbank",
    "indicator_code": "FP.CPI.TOTL.ZG",
    "period": "2016-01-01",
    "value": 0.250000000000031,
    "meta": {
      "unit": "",
      "obs_status": "",
      "decimal": 1,
      "country_name": "Denmark",
      "indicator_name": "Inflation, consumer prices (annual %)"
    }
  },
  {
    "country_iso2": "DK",
    "source": "worldbank",
    "indicator_code": "FP.CPI.TOTL.ZG",
    "period": "2015-01-01",
    "value": 0.452034153691575,
    "meta": {
      "unit": "",
      "obs_status": "",
      "decimal": 1,
      "country_name": "Denmark",
      "indicator_name": "Inflation, consumer prices (annual %)"
    }
  },
  {
    "country_iso2": "DK",
    "source": "worldbank",
    "indicator_code": "SL.UEM.TOTL.ZS",
    "period": "2024-01-01",
    "value": 5.587,
    "meta": {
      "unit": "",
      "obs_status": "",
      "decimal": 1,
      "country_name": "Denmark",
      "indicator_name": "Unemployment, total (% of total labor force) (modeled ILO estimate)"
    }
  },
  {
    "country_iso2": "DK",
    "source": "worldbank",
    "indicator_code": "SL.UEM.TOTL.ZS",
    "period": "2023-01-01",
    "value": 5.094,
    "meta": {
      "unit": "",
      "obs_status": "",
      "decimal": 1,
      "country_name": "Denmark",
      "indicator_name": "Unemployment, total (% of total labor force) (modeled ILO estimate)"
    }
  },
  {
    "country_iso2": "DK",
    "source": "worldbank",
    "indicator_code": "SL.UEM.TOTL.ZS",
    "period": "2022-01-01",
    "value": 4.434,
    "meta": {
      "unit": "",
      "obs_status": "",
      "decimal": 1,
      "country_name": "Denmark",
      "indicator_name": "Unemployment, total (% of total labor force) (modeled ILO estimate)"
    }
  },
  {
    "country_iso2": "DK",
    "source": "worldbank",
    "indicator_code": "SL.UEM.TOTL.ZS",
    "period": "2021-01-01",
    "value": 5.043,
    "meta": {
      "unit": "",
      "obs_status": "",
      "decimal": 1,
      "country_name": "Denmark",
      "indicator_name": "Unemployment, total (% of total labor force) (modeled ILO estimate)"
    }
  },
  {
    "country_iso2": "DK",
    "source": "worldbank",
    "indicator_code": "SL.UEM.TOTL.ZS",
    "period": "2020-01-01",
    "value": 5.637,
    "meta": {
      "unit": "",
      "obs_status": "",
      "decimal": 1,
      "country_name": "Denmark",
      "indicator_name": "Unemployment, total (% of total labor force) (modeled ILO estimate)"
    }
  },
  {
    "country_iso2": "DK",
    "source": "worldbank",
    "indicator_code": "SL.UEM.TOTL.ZS",
    "period": "2019-01-01",
    "value": 5.018,
    "meta": {
      "unit": "",
      "obs_status": "",
      "decimal": 1,
      "country_name": "Denmark",
      "indicator_name": "Unemployment, total (% of total labor force) (modeled ILO estimate)"
    }
  },
  {
    "country_iso2": "DK",
    "source": "worldbank",
    "indicator_code": "SL.UEM.TOTL.ZS",
    "period": "2018-01-01",
    "value": 5.131,
    "meta": {
      "unit": "",
      "obs_status": "",
      "decimal": 1,
      "country_name": "Denmark",
      "indicator_name": "Unemployment, total (% of total labor force) (modeled ILO estimate)"
    }
  },
  {
    "country_iso2": "DK",
    "source": "worldbank",
    "indicator_code": "SL.UEM.TOTL.ZS",
    "period": "2017-01-01",
    "value": 5.833,
    "meta": {
      "unit": "",
      "obs_status": "",
      "decimal": 1,
      "country_name": "Denmark",
      "indicator_name": "Unemployment, total (% of total labor force) (modeled ILO estimate)"
    }
  },
  {
    "country_iso2": "DK",
    "source": "worldbank",
    "indicator_code": "SL.UEM.TOTL.ZS",
    "period": "2016-01-01",
    "value": 5.989,
    "meta": {
      "unit": "",
      "obs_status": "",
      "decimal": 1,
      "country_name": "Denmark",
      "indicator_name": "Unemployment, total (% of total labor force) (modeled ILO estimate)"
    }
  },
  {
    "country_iso2": "DK",
    "source": "worldbank",
    "indicator_code": "SL.UEM.TOTL.ZS",
    "period": "2015-01-01",
    "value": 6.278,
    "meta": {
      "unit": "",
      "obs_status": "",
      "decimal": 1,
      "country_name": "Denmark",
      "indicator_name": "Unemployment, total (% of total labor force) (modeled ILO estimate)"
    }
  },
  {
    "country_iso2": "DK",
    "source": "worldbank",
    "indicator_code": "SP.DYN.LE00.IN",
    "period": "2024-01-01",
    "value": null,
    "meta": {
      "unit": "",
      "obs_status": "",
      "decimal": 0,
      "country_name": "Denmark",
      "indicator_name": "Life expectancy at birth, total (years)"
    }
  },
  {
    "country_iso2": "DK",
    "source": "worldbank",
    "indicator_code": "SP.DYN.LE00.IN",
    "period": "2023-01-01",
    "value": 81.8536585365854,
    "meta": {
      "unit": "",
      "obs_status": "",
      "decimal": 0,
      "country_name": "Denmark",
      "indicator_name": "Life expectancy at birth, total (years)"
    }
  },
  {
    "country_iso2": "DK",
    "source": "worldbank",
    "indicator_code": "SP.DYN.LE00.IN",
    "period": "2022-01-01",
    "value": 81.3048780487805,
    "meta": {
      "unit": "",
      "obs_status": "",
      "decimal": 0,
      "country_name": "Denmark",
      "indicator_name": "Life expectancy at birth, total (years)"
    }
  },
  {
    "country_iso2": "DK",
    "source": "worldbank",
    "indicator_code": "SP.DYN.LE00.IN",
    "period": "2021-01-01",
    "value": 81.4048780487805,
    "meta": {
      "unit": "",
      "obs_status": "",
      "decimal": 0,
      "country_name": "Denmark",
      "indicator_name": "Life expectancy at birth, total (years)"
    }
  },
  {
    "country_iso2": "DK",
    "source": "worldbank",
    "indicator_code": "SP.DYN.LE00.IN",
    "period": "2020-01-01",
    "value": 81.6024390243903,
    "meta": {
      "unit": "",
      "obs_status": "",
      "decimal": 0,
      "country_name": "Denmark",
      "indicator_name": "Life expectancy at birth, total (years)"
    }
  },
  {
    "country_iso2": "DK",
    "source": "worldbank",
    "indicator_code": "SP.DYN.LE00.IN",
    "period": "2019-01-01",
    "value": 81.4512195121951,
    "meta": {
      "unit": "",
      "obs_status": "",
      "decimal": 0,
      "country_name": "Denmark",
      "indicator_name": "Life expectancy at birth, total (years)"
    }
  },
  {
    "country_iso2": "DK",
    "source": "worldbank",
    "indicator_code": "SP.DYN.LE00.IN",
    "period": "2018-01-01",
    "value": 80.9536585365854,
    "meta": {
      "unit": "",
      "obs_status": "",
      "decimal": 0,
      "country_name": "Denmark",
      "indicator_name": "Life expectancy at birth, total (years)"
    }
  },
  {
    "country_iso2": "DK",
    "source": "worldbank",
    "indicator_code": "SP.DYN.LE00.IN",
    "period": "2017-01-01",
    "value": 81.1024390243903,
    "meta": {
      "unit": "",
      "obs_status": "",
      "decimal": 0,
      "country_name": "Denmark",
      "indicator_name": "Life expectancy at birth, total (years)"
    }
  },
  {
    "country_iso2": "DK",
    "source": "worldbank",
    "indicator_code": "SP.DYN.LE00.IN",
    "period": "2016-01-01",
    "value": 80.8536585365854,
    "meta": {
      "unit": "",
      "obs_status": "",
      "decimal": 0,
      "country_name": "Denmark",
      "indicator_name": "Life expectancy at birth, total (years)"
    }
  },
  {
    "country_iso2": "DK",
    "source": "worldbank",
    "indicator_code": "SP.DYN.LE00.IN",
    "period": "2015-01-01",
    "value": 80.7024390243902,
    "meta": {
      "unit": "",
      "obs_status": "",
      "decimal": 0,
      "country_name": "Denmark",
      "indicator_name": "Life expectancy at birth, total (years)"
    }
  },
  {
    "country_iso2": "DK",
    "source": "worldbank",
    "indicator_code": "SP.POP.TOTL",
    "period": "2024-01-01",
    "value": 5976992,
    "meta": {
      "unit": "",
      "obs_status": "",
      "decimal": 0,
      "country_name": "Denmark",
      "indicator_name": "Population, total"
    }
  },
  {
    "country_iso2": "DK",
    "source": "worldbank",
    "indicator_code": "SP.POP.TOTL",
    "period": "2023-01-01",
    "value": 5946952,
    "meta": {
      "unit": "",
      "obs_status": "",
      "decimal": 0,
      "country_name": "Denmark",
      "indicator_name": "Population, total"
    }
  },
  {
    "country_iso2": "DK",
    "source": "worldbank",
    "indicator_code": "SP.POP.TOTL",
    "period": "2022-01-01",
    "value": 5903037,
    "meta": {
      "unit": "",
      "obs_status": "",
      "decimal": 0,
      "country_name": "Denmark",
      "indicator_name": "Population, total"
    }
  },
  {
    "country_iso2": "DK",
    "source": "worldbank",
    "indicator_code": "SP.POP.TOTL",
    "period": "2021-01-01",
    "value": 5856733,
    "meta": {
      "unit": "",
      "obs_status": "",
      "decimal": 0,
      "country_name": "Denmark",
      "indicator_name": "Population, total"
    }
  },
  {
    "country_iso2": "DK",
    "source": "worldbank",
    "indicator_code": "SP.POP.TOTL",
    "period": "2020-01-01",
    "value": 5831404,
    "meta": {
      "unit": "",
      "obs_status": "",
      "decimal": 0,
      "country_name": "Denmark",
      "indicator_name": "Population, total"
    }
  },
  {
    "country_iso2": "DK",
    "source": "worldbank",
    "indicator_code": "SP.POP.TOTL",
    "period": "2019-01-01",
    "value": 5814422,
    "meta": {
      "unit": "",
      "obs_status": "",
      "decimal": 0,
      "country_name": "Denmark",
      "indicator_name": "Population, total"
    }
  },
  {
    "country_iso2": "DK",
    "source": "worldbank",
    "indicator_code": "SP.POP.TOTL",
    "period": "2018-01-01",
    "value": 5793636,
    "meta": {
      "unit": "",
      "obs_status": "",
      "decimal": 0,
      "country_name": "Denmark",
      "indicator_name": "Population, total"
    }
  },
  {
    "country_iso2": "DK",
    "source": "worldbank",
    "indicator_code": "SP.POP.TOTL",
    "period": "2017-01-01",
    "value": 5764980,
    "meta": {
      "unit": "",
      "obs_status": "",
      "decimal": 0,
      "country_name": "Denmark",
      "indicator_name": "Population, total"
    }
  },
  {
    "country_iso2": "DK",
    "source": "worldbank",
    "indicator_code": "SP.POP.TOTL",
    "period": "2016-01-01",
    "value": 5728010,
    "meta": {
      "unit": "",
      "obs_status": "",
      "decimal": 0,
      "country_name": "Denmark",
      "indicator_name": "Population, total"
    }
  },
  {
    "country_iso2": "DK",
    "source": "worldbank",
    "indicator_code": "SP.POP.TOTL",
    "period": "2015-01-01",
    "value": 5683483,
    "meta": {
      "unit": "",
      "obs_status": "",
      "decimal": 0,
      "country_name": "Denmark",
      "indicator_name": "Population, total"
    }
  },
  {
    "country_iso2": "DK",
    "source": "worldbank",
    "indicator_code": "SP.URB.TOTL.IN.ZS",
    "period": "2024-01-01",
    "value": 88.626,
    "meta": {
      "unit": "",
      "obs_status": "",
      "decimal": 0,
      "country_name": "Denmark",
      "indicator_name": "Urban population (% of total population)"
    }
  },
  {
    "country_iso2": "DK",
    "source": "worldbank",
    "indicator_code": "SP.URB.TOTL.IN.ZS",
    "period": "2023-01-01",
    "value": 88.495,
    "meta": {
      "unit": "",
      "obs_status": "",
      "decimal": 0,
      "country_name": "Denmark",
      "indicator_name": "Urban population (% of total population)"
    }
  },
  {
    "country_iso2": "DK",
    "source": "worldbank",
    "indicator_code": "SP.URB.TOTL.IN.ZS",
    "period": "2022-01-01",
    "value": 88.367,
    "meta": {
      "unit": "",
      "obs_status": "",
      "decimal": 0,
      "country_name": "Denmark",
      "indicator_name": "Urban population (% of total population)"
    }
  },
  {
    "country_iso2": "DK",
    "source": "worldbank",
    "indicator_code": "SP.URB.TOTL.IN.ZS",
    "period": "2021-01-01",
    "value": 88.24,
    "meta": {
      "unit": "",
      "obs_status": "",
      "decimal": 0,
      "country_name": "Denmark",
      "indicator_name": "Urban population (% of total population)"
    }
  },
  {
    "country_iso2": "DK",
    "source": "worldbank",
    "indicator_code": "SP.URB.TOTL.IN.ZS",
    "period": "2020-01-01",
    "value": 88.116,
    "meta": {
      "unit": "",
      "obs_status": "",
      "decimal": 0,
      "country_name": "Denmark",
      "indicator_name": "Urban population (% of total population)"
    }
  },
  {
    "country_iso2": "DK",
    "source": "worldbank",
    "indicator_code": "SP.URB.TOTL.IN.ZS",
    "period": "2019-01-01",
    "value": 87.994,
    "meta": {
      "unit": "",
      "obs_status": "",
      "decimal": 0,
      "country_name": "Denmark",
      "indicator_name": "Urban population (% of total population)"
    }
  },
  {
    "country_iso2": "DK",
    "source": "worldbank",
    "indicator_code": "SP.URB.TOTL.IN.ZS",
    "period": "2018-01-01",
    "value": 87.874,
    "meta": {
      "unit": "",
      "obs_status": "",
      "decimal": 0,
      "country_name": "Denmark",
      "indicator_name": "Urban population (% of total population)"
    }
  },
  {
    "country_iso2": "DK",
    "source": "worldbank",
    "indicator_code": "SP.URB.TOTL.IN.ZS",
    "period": "2017-01-01",
    "value": 87.757,
    "meta": {
      "unit": "",
      "obs_status": "",
      "decimal": 0,
      "country_name": "Denmark",
      "indicator_name": "Urban population (% of total population)"
    }
  },
  {
    "country_iso2": "DK",
    "source": "worldbank",
    "indicator_code": "SP.URB.TOTL.IN.ZS",
    "period": "2016-01-01",
    "value": 87.642,
    "meta": {
      "unit": "",
      "obs_status": "",
      "decimal": 0,
      "country_name": "Denmark",
      "indicator_name": "Urban population (% of total population)"
    }
  },
  {
    "country_iso2": "DK",
    "source": "worldbank",
    "indicator_code": "SP.URB.TOTL.IN.ZS",
    "period": "2015-01-01",
    "value": 87.526,
    "meta": {
      "unit": "",
      "obs_status": "",
      "decimal": 0,
      "country_name": "Denmark",
      "indicator_name": "Urban population (% of total population)"
    }
  },
  {
    "country_iso2": "DK",
    "source": "worldbank",
    "indicator_code": "SE.ADT.LITR.ZS",
    "period": "2024-01-01",
    "value": null,
    "meta": {
      "unit": "",
      "obs_status": "",
      "decimal": 0,
      "country_name": "Denmark",
      "indicator_name": "Literacy rate, adult total (% of people ages 15 and above)"
    }
  },
  {
    "country_iso2": "DK",
    "source": "worldbank",
    "indicator_code": "SE.ADT.LITR.ZS",
    "period": "2023-01-01",
    "value": null,
    "meta": {
      "unit": "",
      "obs_status": "",
      "decimal": 0,
      "country_name": "Denmark",
      "indicator_name": "Literacy rate, adult total (% of people ages 15 and above)"
    }
  },
  {
    "country_iso2": "DK",
    "source": "worldbank",
    "indicator_code": "SE.ADT.LITR.ZS",
    "period": "2022-01-01",
    "value": null,
    "meta": {
      "unit": "",
      "obs_status": "",
      "decimal": 0,
      "country_name": "Denmark",
      "indicator_name": "Literacy rate, adult total (% of people ages 15 and above)"
    }
  },
  {
    "country_iso2": "DK",
    "source": "worldbank",
    "indicator_code": "SE.ADT.LITR.ZS",
    "period": "2021-01-01",
    "value": null,
    "meta": {
      "unit": "",
      "obs_status": "",
      "decimal": 0,
      "country_name": "Denmark",
      "indicator_name": "Literacy rate, adult total (% of people ages 15 and above)"
    }
  },
  {
    "country_iso2": "DK",
    "source": "worldbank",
    "indicator_code": "SE.ADT.LITR.ZS",
    "period": "2020-01-01",
    "value": null,
    "meta": {
      "unit": "",
      "obs_status": "",
      "decimal": 0,
      "country_name": "Denmark",
      "indicator_name": "Literacy rate, adult total (% of people ages 15 and above)"
    }
  },
  {
    "country_iso2": "DK",
    "source": "worldbank",
    "indicator_code": "SE.ADT.LITR.ZS",
    "period": "2019-01-01",
    "value": null,
    "meta": {
      "unit": "",
      "obs_status": "",
      "decimal": 0,
      "country_name": "Denmark",
      "indicator_name": "Literacy rate, adult total (% of people ages 15 and above)"
    }
  },
  {
    "country_iso2": "DK",
    "source": "worldbank",
    "indicator_code": "SE.ADT.LITR.ZS",
    "period": "2018-01-01",
    "value": null,
    "meta": {
      "unit": "",
      "obs_status": "",
      "decimal": 0,
      "country_name": "Denmark",
      "indicator_name": "Literacy rate, adult total (% of people ages 15 and above)"
    }
  },
  {
    "country_iso2": "DK",
    "source": "worldbank",
    "indicator_code": "SE.ADT.LITR.ZS",
    "period": "2017-01-01",
    "value": null,
    "meta": {
      "unit": "",
      "obs_status": "",
      "decimal": 0,
      "country_name": "Denmark",
      "indicator_name": "Literacy rate, adult total (% of people ages 15 and above)"
    }
  },
  {
    "country_iso2": "DK",
    "source": "worldbank",
    "indicator_code": "SE.ADT.LITR.ZS",
    "period": "2016-01-01",
    "value": null,
    "meta": {
      "unit": "",
      "obs_status": "",
      "decimal": 0,
      "country_name": "Denmark",
      "indicator_name": "Literacy rate, adult total (% of people ages 15 and above)"
    }
  },
  {
    "country_iso2": "DK",
    "source": "worldbank",
    "indicator_code": "SE.ADT.LITR.ZS",
    "period": "2015-01-01",
    "value": null,
    "meta": {
      "unit": "",
      "obs_status": "",
      "decimal": 0,
      "country_name": "Denmark",
      "indicator_name": "Literacy rate, adult total (% of people ages 15 and above)"
    }
  },
  {
    "country_iso2": "DK",
    "source": "worldbank",
    "indicator_code": "AG.LND.FRST.ZS",
    "period": "2024-01-01",
    "value": null,
    "meta": {
      "unit": "",
      "obs_status": "",
      "decimal": 1,
      "country_name": "Denmark",
      "indicator_name": "Forest area (% of land area)"
    }
  },
  {
    "country_iso2": "DK",
    "source": "worldbank",
    "indicator_code": "AG.LND.FRST.ZS",
    "period": "2023-01-01",
    "value": null,
    "meta": {
      "unit": "",
      "obs_status": "",
      "decimal": 1,
      "country_name": "Denmark",
      "indicator_name": "Forest area (% of land area)"
    }
  },
  {
    "country_iso2": "DK",
    "source": "worldbank",
    "indicator_code": "AG.LND.FRST.ZS",
    "period": "2022-01-01",
    "value": 15.758,
    "meta": {
      "unit": "",
      "obs_status": "",
      "decimal": 1,
      "country_name": "Denmark",
      "indicator_name": "Forest area (% of land area)"
    }
  },
  {
    "country_iso2": "DK",
    "source": "worldbank",
    "indicator_code": "AG.LND.FRST.ZS",
    "period": "2021-01-01",
    "value": 15.7345,
    "meta": {
      "unit": "",
      "obs_status": "",
      "decimal": 1,
      "country_name": "Denmark",
      "indicator_name": "Forest area (% of land area)"
    }
  },
  {
    "country_iso2": "DK",
    "source": "worldbank",
    "indicator_code": "AG.LND.FRST.ZS",
    "period": "2020-01-01",
    "value": 15.711,
    "meta": {
      "unit": "",
      "obs_status": "",
      "decimal": 1,
      "country_name": "Denmark",
      "indicator_name": "Forest area (% of land area)"
    }
  },
  {
    "country_iso2": "DK",
    "source": "worldbank",
    "indicator_code": "AG.LND.FRST.ZS",
    "period": "2019-01-01",
    "value": 15.6875,
    "meta": {
      "unit": "",
      "obs_status": "",
      "decimal": 1,
      "country_name": "Denmark",
      "indicator_name": "Forest area (% of land area)"
    }
  },
  {
    "country_iso2": "DK",
    "source": "worldbank",
    "indicator_code": "AG.LND.FRST.ZS",
    "period": "2018-01-01",
    "value": 15.664,
    "meta": {
      "unit": "",
      "obs_status": "",
      "decimal": 1,
      "country_name": "Denmark",
      "indicator_name": "Forest area (% of land area)"
    }
  },
  {
    "country_iso2": "DK",
    "source": "worldbank",
    "indicator_code": "AG.LND.FRST.ZS",
    "period": "2017-01-01",
    "value": 15.64,
    "meta": {
      "unit": "",
      "obs_status": "",
      "decimal": 1,
      "country_name": "Denmark",
      "indicator_name": "Forest area (% of land area)"
    }
  },
  {
    "country_iso2": "DK",
    "source": "worldbank",
    "indicator_code": "AG.LND.FRST.ZS",
    "period": "2016-01-01",
    "value": 15.6165,
    "meta": {
      "unit": "",
      "obs_status": "",
      "decimal": 1,
      "country_name": "Denmark",
      "indicator_name": "Forest area (% of land area)"
    }
  },
  {
    "country_iso2": "DK",
    "source": "worldbank",
    "indicator_code": "AG.LND.FRST.ZS",
    "period": "2015-01-01",
    "value": 15.617,
    "meta": {
      "unit": "",
      "obs_status": "",
      "decimal": 1,
      "country_name": "Denmark",
      "indicator_name": "Forest area (% of land area)"
    }
  },
  {
    "country_iso2": "DK",
    "source": "worldbank",
    "indicator_code": "EG.FEC.RNEW.ZS",
    "period": "2024-01-01",
    "value": null,
    "meta": {
      "unit": "",
      "obs_status": "",
      "decimal": 2,
      "country_name": "Denmark",
      "indicator_name": "Renewable energy consumption (% of total final energy consumption)"
    }
  },
  {
    "country_iso2": "DK",
    "source": "worldbank",
    "indicator_code": "EG.FEC.RNEW.ZS",
    "period": "2023-01-01",
    "value": null,
    "meta": {
      "unit": "",
      "obs_status": "",
      "decimal": 2,
      "country_name": "Denmark",
      "indicator_name": "Renewable energy consumption (% of total final energy consumption)"
    }
  },
  {
    "country_iso2": "DK",
    "source": "worldbank",
    "indicator_code": "EG.FEC.RNEW.ZS",
    "period": "2022-01-01",
    "value": null,
    "meta": {
      "unit": "",
      "obs_status": "",
      "decimal": 2,
      "country_name": "Denmark",
      "indicator_name": "Renewable energy consumption (% of total final energy consumption)"
    }
  },
  {
    "country_iso2": "DK",
    "source": "worldbank",
    "indicator_code": "EG.FEC.RNEW.ZS",
    "period": "2021-01-01",
    "value": 39.5,
    "meta": {
      "unit": "",
      "obs_status": "",
      "decimal": 2,
      "country_name": "Denmark",
      "indicator_name": "Renewable energy consumption (% of total final energy consumption)"
    }
  },
  {
    "country_iso2": "DK",
    "source": "worldbank",
    "indicator_code": "EG.FEC.RNEW.ZS",
    "period": "2020-01-01",
    "value": 39.5,
    "meta": {
      "unit": "",
      "obs_status": "",
      "decimal": 2,
      "country_name": "Denmark",
      "indicator_name": "Renewable energy consumption (% of total final energy consumption)"
    }
  },
  {
    "country_iso2": "DK",
    "source": "worldbank",
    "indicator_code": "EG.FEC.RNEW.ZS",
    "period": "2019-01-01",
    "value": 37.2,
    "meta": {
      "unit": "",
      "obs_status": "",
      "decimal": 2,
      "country_name": "Denmark",
      "indicator_name": "Renewable energy consumption (% of total final energy consumption)"
    }
  },
  {
    "country_iso2": "DK",
    "source": "worldbank",
    "indicator_code": "EG.FEC.RNEW.ZS",
    "period": "2018-01-01",
    "value": 34.6,
    "meta": {
      "unit": "",
      "obs_status": "",
      "decimal": 2,
      "country_name": "Denmark",
      "indicator_name": "Renewable energy consumption (% of total final energy consumption)"
    }
  },
  {
    "country_iso2": "DK",
    "source": "worldbank",
    "indicator_code": "EG.FEC.RNEW.ZS",
    "period": "2017-01-01",
    "value": 35,
    "meta": {
      "unit": "",
      "obs_status": "",
      "decimal": 2,
      "country_name": "Denmark",
      "indicator_name": "Renewable energy consumption (% of total final energy consumption)"
    }
  },
  {
    "country_iso2": "DK",
    "source": "worldbank",
    "indicator_code": "EG.FEC.RNEW.ZS",
    "period": "2016-01-01",
    "value": 32,
    "meta": {
      "unit": "",
      "obs_status": "",
      "decimal": 2,
      "country_name": "Denmark",
      "indicator_name": "Renewable energy consumption (% of total final energy consumption)"
    }
  },
  {
    "country_iso2": "DK",
    "source": "worldbank",
    "indicator_code": "EG.FEC.RNEW.ZS",
    "period": "2015-01-01",
    "value": 32.5,
    "meta": {
      "unit": "",
      "obs_status": "",
      "decimal": 2,
      "country_name": "Denmark",
      "indicator_name": "Renewable energy consumption (% of total final energy consumption)"
    }
  },
  {
    "country_iso2": "DK",
    "source": "worldbank",
    "indicator_code": "IT.NET.USER.ZS",
    "period": "2024-01-01",
    "value": 99.8,
    "meta": {
      "unit": "",
      "obs_status": "",
      "decimal": 0,
      "country_name": "Denmark",
      "indicator_name": "Individuals using the Internet (% of population)"
    }
  },
  {
    "country_iso2": "DK",
    "source": "worldbank",
    "indicator_code": "IT.NET.USER.ZS",
    "period": "2023-01-01",
    "value": 98.8,
    "meta": {
      "unit": "",
      "obs_status": "",
      "decimal": 0,
      "country_name": "Denmark",
      "indicator_name": "Individuals using the Internet (% of population)"
    }
  },
  {
    "country_iso2": "DK",
    "source": "worldbank",
    "indicator_code": "IT.NET.USER.ZS",
    "period": "2022-01-01",
    "value": 97.9,
    "meta": {
      "unit": "",
      "obs_status": "",
      "decimal": 0,
      "country_name": "Denmark",
      "indicator_name": "Individuals using the Internet (% of population)"
    }
  },
  {
    "country_iso2": "DK",
    "source": "worldbank",
    "indicator_code": "IT.NET.USER.ZS",
    "period": "2021-01-01",
    "value": 98.9,
    "meta": {
      "unit": "",
      "obs_status": "",
      "decimal": 0,
      "country_name": "Denmark",
      "indicator_name": "Individuals using the Internet (% of population)"
    }
  },
  {
    "country_iso2": "DK",
    "source": "worldbank",
    "indicator_code": "IT.NET.USER.ZS",
    "period": "2020-01-01",
    "value": 96.5,
    "meta": {
      "unit": "",
      "obs_status": "",
      "decimal": 0,
      "country_name": "Denmark",
      "indicator_name": "Individuals using the Internet (% of population)"
    }
  },
  {
    "country_iso2": "DK",
    "source": "worldbank",
    "indicator_code": "IT.NET.USER.ZS",
    "period": "2019-01-01",
    "value": 98,
    "meta": {
      "unit": "",
      "obs_status": "",
      "decimal": 0,
      "country_name": "Denmark",
      "indicator_name": "Individuals using the Internet (% of population)"
    }
  },
  {
    "country_iso2": "DK",
    "source": "worldbank",
    "indicator_code": "IT.NET.USER.ZS",
    "period": "2018-01-01",
    "value": 97.3,
    "meta": {
      "unit": "",
      "obs_status": "",
      "decimal": 0,
      "country_name": "Denmark",
      "indicator_name": "Individuals using the Internet (% of population)"
    }
  },
  {
    "country_iso2": "DK",
    "source": "worldbank",
    "indicator_code": "IT.NET.USER.ZS",
    "period": "2017-01-01",
    "value": 97.1,
    "meta": {
      "unit": "",
      "obs_status": "",
      "decimal": 0,
      "country_name": "Denmark",
      "indicator_name": "Individuals using the Internet (% of population)"
    }
  },
  {
    "country_iso2": "DK",
    "source": "worldbank",
    "indicator_code": "IT.NET.USER.ZS",
    "period": "2016-01-01",
    "value": 97,
    "meta": {
      "unit": "",
      "obs_status": "",
      "decimal": 0,
      "country_name": "Denmark",
      "indicator_name": "Individuals using the Internet (% of population)"
    }
  },
  {
    "country_iso2": "DK",
    "source": "worldbank",
    "indicator_code": "IT.NET.USER.ZS",
    "period": "2015-01-01",
    "value": 96.3,
    "meta": {
      "unit": "",
      "obs_status": "",
      "decimal": 0,
      "country_name": "Denmark",
      "indicator_name": "Individuals using the Internet (% of population)"
    }
  },
  {
    "country_iso2": "DK",
    "source": "worldbank",
    "indicator_code": "IT.CEL.SETS.P2",
    "period": "2024-01-01",
    "value": null,
    "meta": {
      "unit": "",
      "obs_status": "",
      "decimal": 0,
      "country_name": "Denmark",
      "indicator_name": "Mobile cellular subscriptions (per 100 people)"
    }
  },
  {
    "country_iso2": "DK",
    "source": "worldbank",
    "indicator_code": "IT.CEL.SETS.P2",
    "period": "2023-01-01",
    "value": 126.919,
    "meta": {
      "unit": "",
      "obs_status": "",
      "decimal": 0,
      "country_name": "Denmark",
      "indicator_name": "Mobile cellular subscriptions (per 100 people)"
    }
  },
  {
    "country_iso2": "DK",
    "source": "worldbank",
    "indicator_code": "IT.CEL.SETS.P2",
    "period": "2022-01-01",
    "value": 126.484,
    "meta": {
      "unit": "",
      "obs_status": "",
      "decimal": 0,
      "country_name": "Denmark",
      "indicator_name": "Mobile cellular subscriptions (per 100 people)"
    }
  },
  {
    "country_iso2": "DK",
    "source": "worldbank",
    "indicator_code": "IT.CEL.SETS.P2",
    "period": "2021-01-01",
    "value": 125.604,
    "meta": {
      "unit": "",
      "obs_status": "",
      "decimal": 0,
      "country_name": "Denmark",
      "indicator_name": "Mobile cellular subscriptions (per 100 people)"
    }
  },
  {
    "country_iso2": "DK",
    "source": "worldbank",
    "indicator_code": "IT.CEL.SETS.P2",
    "period": "2020-01-01",
    "value": 124.37,
    "meta": {
      "unit": "",
      "obs_status": "",
      "decimal": 0,
      "country_name": "Denmark",
      "indicator_name": "Mobile cellular subscriptions (per 100 people)"
    }
  },
  {
    "country_iso2": "DK",
    "source": "worldbank",
    "indicator_code": "IT.CEL.SETS.P2",
    "period": "2019-01-01",
    "value": 124.573,
    "meta": {
      "unit": "",
      "obs_status": "",
      "decimal": 0,
      "country_name": "Denmark",
      "indicator_name": "Mobile cellular subscriptions (per 100 people)"
    }
  },
  {
    "country_iso2": "DK",
    "source": "worldbank",
    "indicator_code": "IT.CEL.SETS.P2",
    "period": "2018-01-01",
    "value": 124.55,
    "meta": {
      "unit": "",
      "obs_status": "",
      "decimal": 0,
      "country_name": "Denmark",
      "indicator_name": "Mobile cellular subscriptions (per 100 people)"
    }
  },
  {
    "country_iso2": "DK",
    "source": "worldbank",
    "indicator_code": "IT.CEL.SETS.P2",
    "period": "2017-01-01",
    "value": 123.862,
    "meta": {
      "unit": "",
      "obs_status": "",
      "decimal": 0,
      "country_name": "Denmark",
      "indicator_name": "Mobile cellular subscriptions (per 100 people)"
    }
  },
  {
    "country_iso2": "DK",
    "source": "worldbank",
    "indicator_code": "IT.CEL.SETS.P2",
    "period": "2016-01-01",
    "value": 121.941,
    "meta": {
      "unit": "",
      "obs_status": "",
      "decimal": 0,
      "country_name": "Denmark",
      "indicator_name": "Mobile cellular subscriptions (per 100 people)"
    }
  },
  {
    "country_iso2": "DK",
    "source": "worldbank",
    "indicator_code": "IT.CEL.SETS.P2",
    "period": "2015-01-01",
    "value": 124.554,
    "meta": {
      "unit": "",
      "obs_status": "",
      "decimal": 0,
      "country_name": "Denmark",
      "indicator_name": "Mobile cellular subscriptions (per 100 people)"
    }
  }
]